{
  "title": "Dinner & Show",
  "banner_image": {
    "name": "Padre_DinnerAndMovie",
    "file_name": "Padre_DinnerAndMovie.jpg",
    "url": "//cdn.traveltripper.io/site-assets/408_410_17879/media/2018-08-01-155200/Padre_DinnerAndMovie.jpg",
    "tags": "",
    "description": "",
    "date_added": "2018-08-01-155200",
    "file_type": "image/jpeg",
    "width": 937,
    "height": 400,
    "file_size": 192596,
    "url_large": "//cdn.traveltripper.io/site-assets/408_410_17879/media/2018-08-01-155200/large_Padre_DinnerAndMovie.jpg",
    "url_medium": "//cdn.traveltripper.io/site-assets/408_410_17879/media/2018-08-01-155200/medium_Padre_DinnerAndMovie.jpg",
    "url_small": "//cdn.traveltripper.io/site-assets/408_410_17879/media/2018-08-01-155200/small_Padre_DinnerAndMovie.jpg",
    "url_xsmall": "//cdn.traveltripper.io/site-assets/408_410_17879/media/2018-08-01-155200/xsmall_Padre_DinnerAndMovie.jpg",
    "url_thumb": "//cdn.traveltripper.io/site-assets/408_410_17879/media/2018-08-01-155200/thumb_Padre_DinnerAndMovie.jpg",
    "path": "//cdn.traveltripper.io/site-assets/408_410_17879/media/2018-08-01-155200/Padre_DinnerAndMovie.jpg",
    "alt": "The Padre Hotel: Dinner & Show Theatre Seats",
    "caption": ""
  },
  "description": "<p>Make a night of it! Catch a movie at <a href=\"http://bit.ly/foxpadre\" target=\"_blank\" rel=\"noopener noreferrer\">Fox Theatre</a> then dine at the Padre. <a href=\"https://www.thepadrehotel.com/dine/brimstone/\" target=\"_blank\" rel=\"noopener noreferrer\">Brimstone</a> offers a free app with purchase to movie goers or enjoy a special 3 course meal at <a href=\"https://www.thepadrehotel.com/dine/belvedere-room/\" target=\"_blank\" rel=\"noopener noreferrer\">Belvedere Room</a> on movie nights.</p>",
  "short_description": "<p>Make a night of it! Catch a movie at <a href=\"http://bit.ly/foxpadre\" target=\"_blank\" rel=\"noopener noreferrer\">Fox Theatre</a> then dine at the Padre. <a href=\"https://www.thepadrehotel.com/dine/brimstone/\" target=\"_blank\" rel=\"noopener noreferrer\">Brimstone</a> offers a free app with purchase to movie goers or enjoy a special 3 course meal at <a href=\"https://www.thepadrehotel.com/dine/belvedere-room/\" target=\"_blank\" rel=\"noopener noreferrer\">Belvedere Room</a> on movie nights.</p>",
  "sort_order": 2,
  "view_event_button_url": "dinner-show"
}